{
  "updatedAt": "2026-05-24T12:09:11.146Z",
  "components": {
    "web": {
      "status": "operational",
      "consecutiveFailures": 0,
      "consecutiveSuccesses": 1298,
      "lastCheckedAt": "2026-05-24T12:09:11.146Z",
      "lastChangedAt": "2026-04-18T18:30:00.000Z"
    },
    "api": {
      "status": "operational",
      "consecutiveFailures": 0,
      "consecutiveSuccesses": 28,
      "lastCheckedAt": "2026-05-24T12:09:11.146Z",
      "lastChangedAt": "2026-05-23T18:57:12.630Z"
    }
  }
}
