{
  "updatedAt": "2026-06-19T18:58:13.607Z",
  "components": {
    "web": {
      "status": "operational",
      "consecutiveFailures": 0,
      "consecutiveSuccesses": 323,
      "lastCheckedAt": "2026-06-19T18:58:13.607Z",
      "lastChangedAt": "2026-05-29T01:18:32.432Z"
    },
    "api": {
      "status": "operational",
      "consecutiveFailures": 0,
      "consecutiveSuccesses": 126,
      "lastCheckedAt": "2026-06-19T18:58:13.607Z",
      "lastChangedAt": "2026-06-09T17:48:59.475Z"
    }
  }
}
