{
  "updatedAt": "2026-07-22T22:02:49.359Z",
  "components": {
    "web": {
      "status": "operational",
      "consecutiveFailures": 0,
      "consecutiveSuccesses": 312,
      "lastCheckedAt": "2026-07-22T22:02:49.359Z",
      "lastChangedAt": "2026-07-15T07:09:06.599Z"
    },
    "api": {
      "status": "operational",
      "consecutiveFailures": 0,
      "consecutiveSuccesses": 27,
      "lastCheckedAt": "2026-07-22T22:02:49.359Z",
      "lastChangedAt": "2026-07-22T06:49:31.025Z"
    }
  }
}
