{
  "updatedAt": "2026-05-05T00:11:45.820Z",
  "components": {
    "web": {
      "status": "operational",
      "consecutiveFailures": 0,
      "consecutiveSuccesses": 651,
      "lastCheckedAt": "2026-05-05T00:11:45.820Z",
      "lastChangedAt": "2026-04-18T18:30:00.000Z"
    },
    "api": {
      "status": "operational",
      "consecutiveFailures": 0,
      "consecutiveSuccesses": 199,
      "lastCheckedAt": "2026-05-05T00:11:45.820Z",
      "lastChangedAt": "2026-04-18T19:47:27.235Z"
    }
  }
}
