{
  "updatedAt": "2026-05-02T09:19:48.405Z",
  "components": {
    "web": {
      "status": "operational",
      "consecutiveFailures": 0,
      "consecutiveSuccesses": 544,
      "lastCheckedAt": "2026-05-02T09:19:48.405Z",
      "lastChangedAt": "2026-04-18T18:30:00.000Z"
    },
    "api": {
      "status": "operational",
      "consecutiveFailures": 0,
      "consecutiveSuccesses": 92,
      "lastCheckedAt": "2026-05-02T09:19:48.405Z",
      "lastChangedAt": "2026-04-18T19:47:27.235Z"
    }
  }
}
