{
  "updatedAt": "2026-05-05T12:47:59.751Z",
  "components": {
    "web": {
      "status": "operational",
      "consecutiveFailures": 0,
      "consecutiveSuccesses": 667,
      "lastCheckedAt": "2026-05-05T12:47:59.751Z",
      "lastChangedAt": "2026-04-18T18:30:00.000Z"
    },
    "api": {
      "status": "operational",
      "consecutiveFailures": 0,
      "consecutiveSuccesses": 215,
      "lastCheckedAt": "2026-05-05T12:47:59.751Z",
      "lastChangedAt": "2026-04-18T19:47:27.235Z"
    }
  }
}
