{
  "updatedAt": "2026-06-26T22:08:47.853Z",
  "components": {
    "web": {
      "status": "operational",
      "consecutiveFailures": 0,
      "consecutiveSuccesses": 514,
      "lastCheckedAt": "2026-06-26T22:08:47.853Z",
      "lastChangedAt": "2026-05-29T01:18:32.432Z"
    },
    "api": {
      "status": "operational",
      "consecutiveFailures": 0,
      "consecutiveSuccesses": 317,
      "lastCheckedAt": "2026-06-26T22:08:47.853Z",
      "lastChangedAt": "2026-06-09T17:48:59.475Z"
    }
  }
}
