{
  "updatedAt": "2026-07-23T16:13:28.135Z",
  "components": {
    "web": {
      "status": "operational",
      "consecutiveFailures": 0,
      "consecutiveSuccesses": 336,
      "lastCheckedAt": "2026-07-23T16:13:28.135Z",
      "lastChangedAt": "2026-07-15T07:09:06.599Z"
    },
    "api": {
      "status": "operational",
      "consecutiveFailures": 0,
      "consecutiveSuccesses": 51,
      "lastCheckedAt": "2026-07-23T16:13:28.135Z",
      "lastChangedAt": "2026-07-22T06:49:31.025Z"
    }
  }
}
