{
  "updatedAt": "2026-06-20T19:25:36.275Z",
  "components": {
    "web": {
      "status": "operational",
      "consecutiveFailures": 0,
      "consecutiveSuccesses": 355,
      "lastCheckedAt": "2026-06-20T19:25:36.275Z",
      "lastChangedAt": "2026-05-29T01:18:32.432Z"
    },
    "api": {
      "status": "operational",
      "consecutiveFailures": 0,
      "consecutiveSuccesses": 158,
      "lastCheckedAt": "2026-06-20T19:25:36.275Z",
      "lastChangedAt": "2026-06-09T17:48:59.475Z"
    }
  }
}
