{
  "updatedAt": "2026-06-18T17:41:22.489Z",
  "components": {
    "web": {
      "status": "operational",
      "consecutiveFailures": 0,
      "consecutiveSuccesses": 300,
      "lastCheckedAt": "2026-06-18T17:41:22.489Z",
      "lastChangedAt": "2026-05-29T01:18:32.432Z"
    },
    "api": {
      "status": "operational",
      "consecutiveFailures": 0,
      "consecutiveSuccesses": 103,
      "lastCheckedAt": "2026-06-18T17:41:22.489Z",
      "lastChangedAt": "2026-06-09T17:48:59.475Z"
    }
  }
}
