{
  "updatedAt": "2026-06-17T15:05:57.622Z",
  "components": {
    "web": {
      "status": "operational",
      "consecutiveFailures": 0,
      "consecutiveSuccesses": 276,
      "lastCheckedAt": "2026-06-17T15:05:57.622Z",
      "lastChangedAt": "2026-05-29T01:18:32.432Z"
    },
    "api": {
      "status": "operational",
      "consecutiveFailures": 0,
      "consecutiveSuccesses": 79,
      "lastCheckedAt": "2026-06-17T15:05:57.622Z",
      "lastChangedAt": "2026-06-09T17:48:59.475Z"
    }
  }
}
